nazk/__init__.py
nazk/exceptions.py
nazk/nazk.py
nazk-1.0.0.dist-info/LICENSE
nazk-1.0.0.dist-info/METADATA
nazk-1.0.0.dist-info/WHEEL
nazk-1.0.0.dist-info/top_level.txt
nazk-1.0.0.dist-info/RECORD
